pysight-0.12.2.dist-info/LICENSE
pysight-0.12.2.dist-info/RECORD
pysight-0.12.2.dist-info/WHEEL
pysight-0.12.2.dist-info/AUTHORS.rst
pysight-0.12.2.dist-info/METADATA
pysight-0.12.2.dist-info/top_level.txt
pysight/read_lst.py
pysight/__init__.py
pysight/main.py
pysight/gui/config_parser.py
pysight/gui/__init__.py
pysight/gui/gui_helpers.py
pysight/gui/gui_main.py
pysight/post_processing/flim.py
pysight/nd_hist_generator/movie.py
pysight/nd_hist_generator/censor_correction.py
pysight/nd_hist_generator/outputs.py
pysight/nd_hist_generator/photon_df.py
pysight/nd_hist_generator/tag_bits.py
pysight/nd_hist_generator/__init__.py
pysight/nd_hist_generator/deinterleave.py
pysight/nd_hist_generator/tag_lens.py
pysight/nd_hist_generator/gating.py
pysight/nd_hist_generator/frame_chunk.py
pysight/nd_hist_generator/volume_gen.py
pysight/nd_hist_generator/allocation.py
pysight/nd_hist_generator/__pycache__/tag_lens.numba_digitize-251.py38.1.nbc
pysight/nd_hist_generator/__pycache__/tag_lens.numba_iterate_over_disordered-282.py37m.2.nbc
pysight/nd_hist_generator/__pycache__/tag_lens.numba_digitize-251.py38.nbi
pysight/nd_hist_generator/__pycache__/censor_correction.numba_bincount-559.py37m.1.nbc
pysight/nd_hist_generator/__pycache__/tag_lens.numba_digitize-251.py38.2.nbc
pysight/nd_hist_generator/__pycache__/tag_lens.numba_iterate_over_disordered-282.py38.1.nbc
pysight/nd_hist_generator/__pycache__/tag_lens.numba_digitize-251.py37m.3.nbc
pysight/nd_hist_generator/__pycache__/tag_lens.numba_iterate_over_disordered-282.py38.nbi
pysight/nd_hist_generator/__pycache__/tag_lens.numba_iterate_over_disordered-282.py37m.1.nbc
pysight/nd_hist_generator/__pycache__/tag_lens.numba_find_phase-259.py37m.nbi
pysight/nd_hist_generator/__pycache__/tag_lens.numba_find_phase-259.py37m.1.nbc
pysight/nd_hist_generator/__pycache__/censor_correction.numba_histogram-554.py38.1.nbc
pysight/nd_hist_generator/__pycache__/tag_lens.numba_find_phase-259.py37m.2.nbc
pysight/nd_hist_generator/__pycache__/tag_lens.numba_find_phase-259.py38.nbi
pysight/nd_hist_generator/__pycache__/censor_correction.numba_histogram-554.py37m.nbi
