Metadata-Version: 2.1
Name: pysight
Version: 0.12.2
Summary: Create images and volumes from photon lists generated by a multiscaler
Home-page: https://github.com/PBLab/python-pysight/
Author: Hagai Har-Gil
Author-email: hagaihargil@protonmail.com
License: Free for non-commercial use
Keywords: multiscaler,photon counting,imaging
Platform: UNKNOWN
Classifier: Development Status :: 3 - Alpha
Classifier: Intended Audience :: Developers
Classifier: License :: Free for non-commercial use
Classifier: Operating System :: Unix
Classifier: Operating System :: POSIX
Classifier: Operating System :: Microsoft :: Windows
Classifier: Programming Language :: Python :: 3
Classifier: Programming Language :: Python :: 3.6
Classifier: Programming Language :: Python :: 3.7
Classifier: Programming Language :: Python :: 3.8
Classifier: Programming Language :: Python :: Implementation :: CPython
Provides-Extra: dev
